aws_croniter/__init__.py
aws_croniter/aws_croniter.py
aws_croniter/exceptions.py
aws_croniter/occurrence.py
aws_croniter/utils.py
aws_croniter-1.0.5.dist-info/LICENSE
aws_croniter-1.0.5.dist-info/METADATA
aws_croniter-1.0.5.dist-info/WHEEL
aws_croniter-1.0.5.dist-info/RECORD
