Metadata-Version: 2.1
Name: aws-croniter
Version: 1.0.5
Summary: A Python utility for AWS cron expressions. Validate and parse AWS EventBridge cron expressions seamlessly.
License: MIT
Author: Siddarth Patil
Author-email: siddarth3639@gmail.com
Requires-Python: >=3.8,<4.0
Classifier: License :: OSI Approved :: MIT License
Classifier: Programming Language :: Python :: 3
Classifier: Programming Language :: Python :: 3.8
Classifier: Programming Language :: Python :: 3.9
Classifier: Programming Language :: Python :: 3.10
Classifier: Programming Language :: Python :: 3.11
Classifier: Programming Language :: Python :: 3.12
Requires-Dist: python-dateutil (>=2.8.1,<3.0.0)
